asyncclick_repl/__init__.py
asyncclick_repl/completer.py
asyncclick_repl/internal_command.py
asyncclick_repl/repl.py
asyncclick_repl-0.1.2.dist-info/METADATA
asyncclick_repl-0.1.2.dist-info/WHEEL
asyncclick_repl-0.1.2.dist-info/licenses/LICENSE
asyncclick_repl-0.1.2.dist-info/RECORD
