Metadata-Version: 2.1
Name: asyncclick-repl
Version: 0.1.2
Summary: Command class to add REPL support to existing click groups
Project-URL: Source, https://github.com/fedej/aio-rom
Author-email: fedej <fede_654_87@hotmail.com>
License-Expression: MIT
License-File: LICENSE
Classifier: Development Status :: 4 - Beta
Classifier: Framework :: AsyncIO
Classifier: Intended Audience :: Developers
Classifier: License :: OSI Approved :: MIT License
Classifier: Operating System :: OS Independent
Classifier: Programming Language :: Python :: 3 :: Only
Classifier: Topic :: Software Development :: Build Tools
Classifier: Topic :: Software Development :: Libraries :: Python Modules
Classifier: Topic :: System :: Shells
Requires-Python: >=3.8
Requires-Dist: anyio<5.0.0,>=4.2.0
Requires-Dist: asyncclick<9,>=8.1.3.4
Requires-Dist: prompt-toolkit<4.0.0,>=3.0.43
Provides-Extra: dev
Requires-Dist: bandit; extra == 'dev'
Requires-Dist: black; extra == 'dev'
Requires-Dist: flake8; extra == 'dev'
Requires-Dist: flake8-bugbear; extra == 'dev'
Requires-Dist: flake8-comprehensions; extra == 'dev'
Requires-Dist: isort; extra == 'dev'
Requires-Dist: mypy; extra == 'dev'
Requires-Dist: pytest; extra == 'dev'
Requires-Dist: pytest-asyncio; extra == 'dev'
